grec
