Metadata-Version: 1.1
Name: grec
Version: 0.2.0
Summary: Colorize terminal text with regular expressions.
Home-page: https://github.com/brisad/grec
Author: Michael Brennan
Author-email: brennan.brisad@gmail.com
License: GPL
Keywords: grec
Platform: UNKNOWN
Classifier: Development Status :: 3 - Alpha
Classifier: Environment :: Console
Classifier: Intended Audience :: Developers
Classifier: License :: OSI Approved :: GNU General Public License v3 (GPLv3)
Classifier: Natural Language :: English
Classifier: Operating System :: POSIX
Classifier: Programming Language :: Python :: 2
Classifier: Programming Language :: Python :: 2.7
